[
    {
        "Collider_Info": {
            "HalfExtents": [
                3.5,
                2.4000000953674316,
                1.7000000476837158
            ],
            "Position": [
                36.20600128173828,
                30.084312438964844,
                22.840999603271484
            ],
            "Radius": 0.5,
            "Rotation": [
                -0.0,
                0.0,
                -0.0
            ],
            "ShapeType": 0
        },
        "Enable_LookAt_Info": {
            "Exit_LookAt_Mask": {
                "ExitLookAtMask": 15
            },
            "Is_LookAt": {
                "CustomData": true,
                "CustomData_Tag": "IsLookAt"
            }
        },
        "Fillter_MyGroup": 128,
        "Fillter_OtherGroupMask": 2,
        "Trigger_ConditionType": 0,
        "Trigger_Coordinate": 1,
        "Trigger_EventTag": "Chapter8_LookAt_Last",
        "Trigger_Type": 8
    }
]