[
  {
    "Type": "PaperSprite",
    "Name": "player_pull_object_ss_0012_X02",
    "Class": "UScriptClass'PaperSprite'",
    "Properties": {
      "BakedSourceUV": {
        "X": 1219.0,
        "Y": 2974.0
      },
      "BakedSourceDimension": {
        "X": 226.0,
        "Y": 267.0
      },
      "BakedSourceTexture": {
        "ObjectName": "Texture2D'Player_2'",
        "ObjectPath": "/Game/Characters/Player/SpriteSheet/Textures/Player_2.0"
      },
      "DefaultMaterial": {
        "ObjectName": "MaterialInstanceConstant'TranslucentUnlitSpriteMaterial'",
        "ObjectPath": "/Paper2D/TranslucentUnlitSpriteMaterial.0"
      },
      "SpriteCollisionDomain": "ESpriteCollisionMode::None",
      "PixelsPerUnrealUnit": 1.0,
      "BakedRenderData": [
        {
          "X": 87.0,
          "Y": 254.0,
          "Z": 0.35253906,
          "W": 0.72631836
        },
        {
          "X": -137.0,
          "Y": 254.0,
          "Z": 0.29785156,
          "W": 0.72631836
        },
        {
          "X": -137.0,
          "Y": -11.0,
          "Z": 0.29785156,
          "W": 0.7910156
        },
        {
          "X": 87.0,
          "Y": -11.0,
          "Z": 0.35253906,
          "W": 0.7910156
        },
        {
          "X": 87.0,
          "Y": 254.0,
          "Z": 0.35253906,
          "W": 0.72631836
        },
        {
          "X": -137.0,
          "Y": -11.0,
          "Z": 0.29785156,
          "W": 0.7910156
        }
      ]
    }
  }
]