[
  {
    "Type": "PaperSprite",
    "Name": "player_c06_powerup_end0031_X01",
    "Class": "UScriptClass'PaperSprite'",
    "Properties": {
      "BakedSourceUV": {
        "X": 2293.0,
        "Y": 1.0
      },
      "BakedSourceDimension": {
        "X": 441.0,
        "Y": 745.0
      },
      "BakedSourceTexture": {
        "ObjectName": "Texture2D'player_c06_swordpowerup-0'",
        "ObjectPath": "/Game/Characters/Player/C06_2122_SwordPowerUp/Textures/player_c06_swordpowerup-0.0"
      },
      "DefaultMaterial": {
        "ObjectName": "MaterialInstanceConstant'TranslucentUnlitSpriteMaterial'",
        "ObjectPath": "/Paper2D/TranslucentUnlitSpriteMaterial.0"
      },
      "SpriteCollisionDomain": "ESpriteCollisionMode::None",
      "PixelsPerUnrealUnit": 1.0,
      "BakedRenderData": [
        {
          "X": 166.0,
          "Y": 732.0,
          "Z": 0.6672363,
          "W": 0.00048828125
        },
        {
          "X": -273.0,
          "Y": 732.0,
          "Z": 0.5600586,
          "W": 0.00048828125
        },
        {
          "X": -273.0,
          "Y": -11.0,
          "Z": 0.5600586,
          "W": 0.18188477
        },
        {
          "X": 166.0,
          "Y": -11.0,
          "Z": 0.6672363,
          "W": 0.18188477
        },
        {
          "X": 166.0,
          "Y": 732.0,
          "Z": 0.6672363,
          "W": 0.00048828125
        },
        {
          "X": -273.0,
          "Y": -11.0,
          "Z": 0.5600586,
          "W": 0.18188477
        }
      ]
    }
  }
]