[
  {
    "Type": "BodySetup",
    "Name": "BodySetup_1",
    "Outer": "Moonbeard_Ch03_Runetooth_Turn_0005_X02",
    "Class": "UScriptClass'BodySetup'",
    "Flags": "RF_Transactional | RF_WasLoaded | RF_LoadCompleted",
    "Properties": {
      "AggGeom": {
        "BoxElems": [
          {
            "Center": {
              "X": -30.5,
              "Y": 0.0,
              "Z": 159.5
            },
            "Rotation": {
              "Pitch": 0.0,
              "Yaw": 0.0,
              "Roll": 0.0
            },
            "X": 345.0,
            "Y": 10.0,
            "Z": 379.0,
            "RestOffset": 0.0,
            "Name": "None",
            "bContributeToMass": true,
            "CollisionEnabled": "ECollisionEnabled::QueryAndPhysics"
          }
        ]
      },
      "DefaultInstance": {
        "ObjectType": "ECC_WorldDynamic",
        "CollisionProfileName": "BlockAllDynamic"
      },
      "CollisionTraceFlag": "CTF_UseSimpleAsComplex"
    },
    "BodySetupGuid": "AF545034439C4B78CA67C49D4F6DB061"
  },
  {
    "Type": "PaperSprite",
    "Name": "Moonbeard_Ch03_Runetooth_Turn_0005_X02",
    "Class": "UScriptClass'PaperSprite'",
    "Flags": "RF_Public | RF_Standalone | RF_Transactional | RF_WasLoaded | RF_LoadCompleted",
    "Properties": {
      "BakedSourceUV": {
        "X": 1068.0,
        "Y": 391.0
      },
      "BakedSourceDimension": {
        "X": 347.0,
        "Y": 381.0
      },
      "BakedSourceTexture": {
        "ObjectName": "Texture2D'moonbeard_c03_runetooth--0'",
        "ObjectPath": "/Game/Characters/Friends/Moonbeard/C03/Textures/moonbeard_c03_runetooth--0.0"
      },
      "DefaultMaterial": {
        "ObjectName": "MaterialInstanceConstant'TranslucentUnlitSpriteMaterial'",
        "ObjectPath": "/Paper2D/TranslucentUnlitSpriteMaterial.0"
      },
      "PixelsPerUnrealUnit": 1.0,
      "BodySetup": {
        "ObjectName": "BodySetup'Moonbeard_Ch03_Runetooth_Turn_0005_X02:BodySetup_1'",
        "ObjectPath": "/Game/Characters/Friends/Moonbeard/C03/Frames/Moonbeard_Ch03_Runetooth_Turn_0005_X02.0"
      },
      "BakedRenderData": [
        {
          "X": 142.0,
          "Y": 349.0,
          "Z": 0.6904297,
          "W": 0.19140625
        },
        {
          "X": -203.0,
          "Y": 349.0,
          "Z": 0.52197266,
          "W": 0.19140625
        },
        {
          "X": -203.0,
          "Y": -30.0,
          "Z": 0.52197266,
          "W": 0.37646484
        },
        {
          "X": 142.0,
          "Y": -30.0,
          "Z": 0.6904297,
          "W": 0.37646484
        },
        {
          "X": 142.0,
          "Y": 349.0,
          "Z": 0.6904297,
          "W": 0.19140625
        },
        {
          "X": -203.0,
          "Y": -30.0,
          "Z": 0.52197266,
          "W": 0.37646484
        }
      ]
    }
  }
]