[
  {
    "Type": "PaperSprite",
    "Name": "Moonbeard_death_0019_X02",
    "Class": "UScriptClass'PaperSprite'",
    "Flags": "RF_Public | RF_Standalone | RF_Transactional | RF_WasLoaded | RF_LoadCompleted",
    "Properties": {
      "BakedSourceUV": {
        "X": 856.0,
        "Y": 1364.0
      },
      "BakedSourceDimension": {
        "X": 529.0,
        "Y": 593.0
      },
      "BakedSourceTexture": {
        "ObjectName": "Texture2D'moonbeard_chp_08_seq_11-2'",
        "ObjectPath": "/Game/Characters/Friends/Moonbeard/Ch08_Seq11/Textures/moonbeard_chp_08_seq_11-2.0"
      },
      "DefaultMaterial": {
        "ObjectName": "MaterialInstanceConstant'TranslucentUnlitSpriteMaterial'",
        "ObjectPath": "/Paper2D/TranslucentUnlitSpriteMaterial.0"
      },
      "SpriteCollisionDomain": "ESpriteCollisionMode::None",
      "PixelsPerUnrealUnit": 1.0,
      "BakedRenderData": [
        {
          "X": 352.0,
          "Y": 498.0,
          "Z": 0.33789062,
          "W": 0.33325195
        },
        {
          "X": -175.0,
          "Y": 498.0,
          "Z": 0.20922852,
          "W": 0.33325195
        },
        {
          "X": -175.0,
          "Y": -93.0,
          "Z": 0.20922852,
          "W": 0.47753906
        },
        {
          "X": 352.0,
          "Y": -93.0,
          "Z": 0.33789062,
          "W": 0.47753906
        },
        {
          "X": 352.0,
          "Y": 498.0,
          "Z": 0.33789062,
          "W": 0.33325195
        },
        {
          "X": -175.0,
          "Y": -93.0,
          "Z": 0.20922852,
          "W": 0.47753906
        }
      ]
    }
  }
]