[
  {
    "Type": "PaperSprite",
    "Name": "MTM_JumpinV02_0013",
    "Class": "UScriptClass'PaperSprite'",
    "Flags": "RF_Public | RF_Standalone | RF_Transactional | RF_WasLoaded | RF_LoadCompleted",
    "Properties": {
      "BakedSourceUV": {
        "X": 1841.0,
        "Y": 1.0
      },
      "BakedSourceDimension": {
        "X": 430.0,
        "Y": 460.0
      },
      "BakedSourceTexture": {
        "ObjectName": "Texture2D'MTM_C09_129130_02-0'",
        "ObjectPath": "/Game/Characters/Friends/Moonbeard/C09_129130/Textures/MTM_C09_129130_02-0.0"
      },
      "DefaultMaterial": {
        "ObjectName": "MaterialInstanceConstant'TranslucentUnlitSpriteMaterial'",
        "ObjectPath": "/Paper2D/TranslucentUnlitSpriteMaterial.0"
      },
      "SpriteCollisionDomain": "ESpriteCollisionMode::None",
      "PixelsPerUnrealUnit": 1.0,
      "BakedRenderData": [
        {
          "X": 155.0,
          "Y": 431.0,
          "Z": 0.5541992,
          "W": 0.00048828125
        },
        {
          "X": -273.0,
          "Y": 431.0,
          "Z": 0.44970703,
          "W": 0.00048828125
        },
        {
          "X": -273.0,
          "Y": -27.0,
          "Z": 0.44970703,
          "W": 0.11230469
        },
        {
          "X": 155.0,
          "Y": -27.0,
          "Z": 0.5541992,
          "W": 0.11230469
        },
        {
          "X": 155.0,
          "Y": 431.0,
          "Z": 0.5541992,
          "W": 0.00048828125
        },
        {
          "X": -273.0,
          "Y": -27.0,
          "Z": 0.44970703,
          "W": 0.11230469
        }
      ]
    }
  }
]