[
  {
    "Type": "PaperSprite",
    "Name": "MTM_Idle_Down_0004",
    "Class": "UScriptClass'PaperSprite'",
    "Flags": "RF_Public | RF_Standalone | RF_Transactional | RF_WasLoaded | RF_LoadCompleted",
    "Properties": {
      "BakedSourceUV": {
        "X": 1633.0,
        "Y": 2912.0
      },
      "BakedSourceDimension": {
        "X": 266.0,
        "Y": 408.0
      },
      "BakedSourceTexture": {
        "ObjectName": "Texture2D'MTM_C09_129130-3'",
        "ObjectPath": "/Game/Characters/Friends/Moonbeard/C09_129130/Textures/MTM_C09_129130-3.0"
      },
      "DefaultMaterial": {
        "ObjectName": "MaterialInstanceConstant'TranslucentUnlitSpriteMaterial'",
        "ObjectPath": "/Paper2D/TranslucentUnlitSpriteMaterial.0"
      },
      "SpriteCollisionDomain": "ESpriteCollisionMode::None",
      "PixelsPerUnrealUnit": 1.0,
      "BakedRenderData": [
        {
          "X": 153.0,
          "Y": 359.0,
          "Z": 0.4633789,
          "W": 0.71118164
        },
        {
          "X": -111.0,
          "Y": 359.0,
          "Z": 0.39892578,
          "W": 0.71118164
        },
        {
          "X": -111.0,
          "Y": -47.0,
          "Z": 0.39892578,
          "W": 0.81030273
        },
        {
          "X": 153.0,
          "Y": -47.0,
          "Z": 0.4633789,
          "W": 0.81030273
        },
        {
          "X": 153.0,
          "Y": 359.0,
          "Z": 0.4633789,
          "W": 0.71118164
        },
        {
          "X": -111.0,
          "Y": -47.0,
          "Z": 0.39892578,
          "W": 0.81030273
        }
      ]
    }
  }
]