[
  {
    "Type": "PaperSprite",
    "Name": "player_c06_powerup_end0007_X02",
    "Class": "UScriptClass'PaperSprite'",
    "Properties": {
      "BakedSourceUV": {
        "X": 1436.0,
        "Y": 1.0
      },
      "BakedSourceDimension": {
        "X": 322.0,
        "Y": 263.0
      },
      "BakedSourceTexture": {
        "ObjectName": "Texture2D'player_c06_swordpowerup-1'",
        "ObjectPath": "/Game/Characters/Player/C06_2122_SwordPowerUp/Textures/player_c06_swordpowerup-1.0"
      },
      "DefaultMaterial": {
        "ObjectName": "MaterialInstanceConstant'TranslucentUnlitSpriteMaterial'",
        "ObjectPath": "/Paper2D/TranslucentUnlitSpriteMaterial.0"
      },
      "SpriteCollisionDomain": "ESpriteCollisionMode::None",
      "PixelsPerUnrealUnit": 1.0,
      "BakedRenderData": [
        {
          "X": 217.0,
          "Y": 241.0,
          "Z": 0.85791016,
          "W": 0.0009765625
        },
        {
          "X": -103.0,
          "Y": 241.0,
          "Z": 0.70166016,
          "W": 0.0009765625
        },
        {
          "X": -103.0,
          "Y": -20.0,
          "Z": 0.70166016,
          "W": 0.12841797
        },
        {
          "X": 217.0,
          "Y": -20.0,
          "Z": 0.85791016,
          "W": 0.12841797
        },
        {
          "X": 217.0,
          "Y": 241.0,
          "Z": 0.85791016,
          "W": 0.0009765625
        },
        {
          "X": -103.0,
          "Y": -20.0,
          "Z": 0.70166016,
          "W": 0.12841797
        }
      ]
    }
  }
]