[
  {
    "Type": "PaperSprite",
    "Name": "player_death_down_0012_X02",
    "Class": "UScriptClass'PaperSprite'",
    "Properties": {
      "BakedSourceUV": {
        "X": 1559.0,
        "Y": 613.0
      },
      "BakedSourceDimension": {
        "X": 235.0,
        "Y": 293.0
      },
      "BakedSourceTexture": {
        "ObjectName": "Texture2D'Player_1'",
        "ObjectPath": "/Game/Characters/Player/SpriteSheet/Textures/Player_1.0"
      },
      "DefaultMaterial": {
        "ObjectName": "MaterialInstanceConstant'TranslucentUnlitSpriteMaterial'",
        "ObjectPath": "/Paper2D/TranslucentUnlitSpriteMaterial.0"
      },
      "SpriteCollisionDomain": "ESpriteCollisionMode::None",
      "PixelsPerUnrealUnit": 1.0,
      "BakedRenderData": [
        {
          "X": 174.0,
          "Y": 272.0,
          "Z": 0.43774414,
          "W": 0.14990234
        },
        {
          "X": -59.0,
          "Y": 272.0,
          "Z": 0.38085938,
          "W": 0.14990234
        },
        {
          "X": -59.0,
          "Y": -19.0,
          "Z": 0.38085938,
          "W": 0.22094727
        },
        {
          "X": 174.0,
          "Y": -19.0,
          "Z": 0.43774414,
          "W": 0.22094727
        },
        {
          "X": 174.0,
          "Y": 272.0,
          "Z": 0.43774414,
          "W": 0.14990234
        },
        {
          "X": -59.0,
          "Y": -19.0,
          "Z": 0.38085938,
          "W": 0.22094727
        }
      ]
    }
  }
]