[
  {
    "Type": "PaperSprite",
    "Name": "jump_out_player_zipOut_right_0007_X01",
    "Class": "UScriptClass'PaperSprite'",
    "Properties": {
      "BakedSourceUV": {
        "X": 346.0,
        "Y": 509.0
      },
      "BakedSourceDimension": {
        "X": 318.0,
        "Y": 260.0
      },
      "BakedSourceTexture": {
        "ObjectName": "Texture2D'jotZip_spriteFile-0'",
        "ObjectPath": "/Game/Characters/Player/SpriteSheet/Textures/jotZip_spriteFile-0.0"
      },
      "DefaultMaterial": {
        "ObjectName": "MaterialInstanceConstant'TranslucentUnlitSpriteMaterial'",
        "ObjectPath": "/Paper2D/TranslucentUnlitSpriteMaterial.0"
      },
      "SpriteCollisionDomain": "ESpriteCollisionMode::None",
      "PixelsPerUnrealUnit": 1.0,
      "BakedRenderData": [
        {
          "X": 145.0,
          "Y": 239.0,
          "Z": 0.32373047,
          "W": 0.12451172
        },
        {
          "X": -171.0,
          "Y": 239.0,
          "Z": 0.1694336,
          "W": 0.12451172
        },
        {
          "X": -171.0,
          "Y": -19.0,
          "Z": 0.1694336,
          "W": 0.1875
        },
        {
          "X": 145.0,
          "Y": -19.0,
          "Z": 0.32373047,
          "W": 0.1875
        },
        {
          "X": 145.0,
          "Y": 239.0,
          "Z": 0.32373047,
          "W": 0.12451172
        },
        {
          "X": -171.0,
          "Y": -19.0,
          "Z": 0.1694336,
          "W": 0.1875
        }
      ]
    }
  }
]