[
  {
    "Type": "PaperSprite",
    "Name": "player_trapped_0013_X02",
    "Class": "UScriptClass'PaperSprite'",
    "Properties": {
      "BakedSourceUV": {
        "X": 571.0,
        "Y": 675.0
      },
      "BakedSourceDimension": {
        "X": 221.0,
        "Y": 279.0
      },
      "BakedSourceTexture": {
        "ObjectName": "Texture2D'player_c09_129130-0'",
        "ObjectPath": "/Game/Characters/Player/C09_129130/Textures/player_c09_129130-0.0"
      },
      "DefaultMaterial": {
        "ObjectName": "MaterialInstanceConstant'TranslucentUnlitSpriteMaterial'",
        "ObjectPath": "/Paper2D/TranslucentUnlitSpriteMaterial.0"
      },
      "SpriteCollisionDomain": "ESpriteCollisionMode::None",
      "PixelsPerUnrealUnit": 1.0,
      "BakedRenderData": [
        {
          "X": 149.0,
          "Y": 245.0,
          "Z": 0.38623047,
          "W": 0.16503906
        },
        {
          "X": -70.0,
          "Y": 245.0,
          "Z": 0.27929688,
          "W": 0.16503906
        },
        {
          "X": -70.0,
          "Y": -32.0,
          "Z": 0.27929688,
          "W": 0.23266602
        },
        {
          "X": 149.0,
          "Y": -32.0,
          "Z": 0.38623047,
          "W": 0.23266602
        },
        {
          "X": 149.0,
          "Y": 245.0,
          "Z": 0.38623047,
          "W": 0.16503906
        },
        {
          "X": -70.0,
          "Y": -32.0,
          "Z": 0.27929688,
          "W": 0.23266602
        }
      ]
    }
  }
]